{
  "AppName": "AudioPlaybackConnector2",
  "UnsupportedOS": "Unsupported Operating System",
  "UnsupportedOSDetail": "AudioPlaybackConnector2 requires Windows 10 version 2004 or later.",
  "ExitConfirm": "All connections will be closed.\nExit anyway?",
  "ReconnectOnStart": "Reconnect on next start",
  "Exit": "Exit",
  "BluetoothSettings": "Bluetooth Settings",
  "OpenSettings": "Open Settings",
  "Connecting": "Connecting",
  "Connected": "Connected",
  "RequestTimedOut": "The request timed out",
  "DeniedBySystem": "The operation was denied by the system",
  "UnknownError": "Unknown error",
  "AutoReconnectFailed": "Auto-reconnect failed",
  "Settings_General": "General",
  "Settings_Devices": "Devices",
  "Settings_About": "About",
  "Settings_Language": "Language",
  "Settings_AutoReconnect": "Auto-reconnect on startup",
  "Settings_StartWithWindows": "Start with Windows",
  "Device_AutoReconnect": "Auto-reconnect this device",
  "Device_Forget": "Forget",
  "TrayMenu_SelectDevice": "Select Device",
  "TrayMenu_NoDevices": "No devices found",
  "Disconnect": "Disconnect",
  "Reconnect": "Reconnect",
  "Reconnecting": "Reconnecting",
  "About_Version": "Version 1.0.0",
  "About_Copyright": "Copyright (C) 2026 Noah Meyer",
  "Notification_Connected": "{0} connected",
  "Notification_Disconnected": "{0} disconnected",
  "Notification_AutoReconnect": "{0} reconnecting...",
  "Notification_AutoReconnectFailed": "Connection to {0} failed. Use Reconnect to try again.",
  "Settings_Title": "Settings",
  "Settings_Subtitle": "Device connection and app behavior",
  "Settings_Connection": "Connection",
  "Settings_System": "System",
  "Settings_App": "App",
  "Settings_AutoReconnect_Desc": "Automatically connects to the last used device.",
  "Settings_StartWithWindows_Desc": "Starts the tray app automatically after sign-in.",
  "Settings_PairedDevice": "Paired device",
  "Settings_NoDevices": "No paired devices"
}
