{
  "AppName": "AudioPlaybackConnector2",
  "UnsupportedOS": "不支持的操作系统",
  "UnsupportedOSDetail": "AudioPlaybackConnector2 需要 Windows 10 版本 2004 或更高版本。",
  "ExitConfirm": "所有连接都将关闭。\n仍然要退出吗？",
  "ReconnectOnStart": "下次启动时重新连接",
  "Exit": "退出",
  "BluetoothSettings": "蓝牙设置",
  "OpenSettings": "打开设置",
  "Connecting": "正在连接",
  "Connected": "已连接",
  "RequestTimedOut": "请求超时",
  "DeniedBySystem": "操作被系统拒绝",
  "UnknownError": "未知错误",
  "AutoReconnectFailed": "自动重新连接失败",
  "Settings_General": "常规",
  "Settings_Devices": "设备",
  "Settings_About": "关于",
  "Settings_Language": "语言",
  "Settings_AutoReconnect": "启动时自动重新连接",
  "Settings_StartWithWindows": "开机时启动",
  "Device_AutoReconnect": "自动重新连接此设备",
  "Device_Forget": "忘记",
  "TrayMenu_SelectDevice": "选择设备",
  "TrayMenu_NoDevices": "未找到设备",
  "Disconnect": "断开连接",
  "Reconnect": "重新连接",
  "Reconnecting": "正在重新连接",
  "About_Version": "版本",
  "About_Copyright": "版权所有 (C) 2026 Noah Meyer",
  "Notification_Connected": "{0} 已连接",
  "Notification_Connected_Caption": "如果听不到音频，请尝试重新连接。",
  "Notification_Disconnected": "{0} 已断开连接",
  "Notification_Disconnected_Body": "Bluetooth 音频连接已中断。",
  "Notification_AutoReconnect": "正在重新连接 {0}...",
  "Notification_AutoReconnect_Body": "正在自动重新连接...",
  "Notification_AutoReconnectFailed": "连接到 {0} 失败。请使用重新连接重试。",
  "Notification_AutoReconnectFailed_Title": "连接到 {0} 失败",
  "Notification_AutoReconnectFailed_Body": "多次尝试后已停止自动重新连接。",
  "Notification_AppStarted_Title": "AudioPlaybackConnector2 已启动",
  "Notification_AppStarted_Body": "应用现在正在后台运行。",
  "Notification_Retry": "重试",
  "Notification_UpdateAvailable_Title": "更新 {0} 可用",
  "Notification_UpdateAvailable_Body": "打开 App Installer 以更新 AudioPlaybackConnector2。",
  "Notification_UpdateAvailable_Action": "打开安装程序",
  "Settings_Title": "设置",
  "Settings_Subtitle": "设备连接和应用行为",
  "Settings_Connection": "连接",
  "Settings_System": "系统",
  "Settings_App": "应用",
  "Settings_Updates": "更新",
  "Settings_AutoReconnect_Desc": "自动连接到上次使用的设备。",
  "Settings_StartWithWindows_Desc": "登录后自动启动托盘应用。",
  "Settings_CheckForUpdates": "检查更新",
  "Settings_CheckForUpdates_Desc": "检查最新的 GitHub Release。",
  "Settings_CheckForUpdates_Button": "检查",
  "Settings_OpenAppInstaller": "打开安装程序",
  "Settings_UpdateCurrent_Title": "已是最新",
  "Settings_UpdateCurrent_Message": "你正在使用最新版本。",
  "Settings_UpdateAvailable_Title": "有可用更新",
  "Settings_UpdateAvailable_Message": "版本 {0} 可用。",
  "Settings_UpdateFailed_Title": "更新检查失败",
  "Settings_UpdateFailed_Message": "现在无法检查更新。",
  "Settings_PairedDevice": "已配对设备",
  "Settings_NoDevices": "没有已配对设备",
  "CrashDialogTitle": "AudioPlaybackConnector2 crashed",
  "CrashDialogBody": "AudioPlaybackConnector2 crashed unexpectedly.\n\nError code: 0x{0:08X}\nCrash report: {1}\nMinidump: {2}\n\nYes = Open prefilled GitHub issue\nNo = Open crash folder\nCancel = Close"
}
